LHA_pyarduino/__init__.py
LHA_pyarduino/pyarduino.py
LHA_pyarduino-0.1.dist-info/METADATA
LHA_pyarduino-0.1.dist-info/WHEEL
LHA_pyarduino-0.1.dist-info/top_level.txt
LHA_pyarduino-0.1.dist-info/RECORD
