Metadata-Version: 2.1
Name: LHA-pyarduino
Version: 0.1
Summary: Python functions for controlling Arduino devices
Author: LEE HYUN A
Author-email: lha110@naver.com
Requires-Dist: pyserial
